tuicubserver/__about__.py
tuicubserver/__init__.py
tuicubserver/__main__.py
tuicubserver/tuicubserver.py
tuicubserver/common/__init__.py
tuicubserver/common/config.py
tuicubserver/common/context.py
tuicubserver/common/db.py
tuicubserver/common/errors.py
tuicubserver/common/logger.py
tuicubserver/common/utils.py
tuicubserver/controllers/__init__.py
tuicubserver/controllers/base.py
tuicubserver/controllers/gamerooms.py
tuicubserver/controllers/games.py
tuicubserver/controllers/users.py
tuicubserver/events/__init__.py
tuicubserver/events/api_client.py
tuicubserver/events/connection.py
tuicubserver/events/events.py
tuicubserver/events/server.py
tuicubserver/messages/__init__.py
tuicubserver/messages/client.py
tuicubserver/messages/message.py
tuicubserver/messages/recipents.py
tuicubserver/messages/server.py
tuicubserver/messages/service.py
tuicubserver/models/__init__.py
tuicubserver/models/base.py
tuicubserver/models/db.py
tuicubserver/models/dto.py
tuicubserver/models/game.py
tuicubserver/models/gameroom.py
tuicubserver/models/mapper.py
tuicubserver/models/status.py
tuicubserver/models/user.py
tuicubserver/repositories/__init__.py
tuicubserver/repositories/base.py
tuicubserver/repositories/gamerooms.py
tuicubserver/repositories/games.py
tuicubserver/repositories/users.py
tuicubserver/routes/__init__.py
tuicubserver/routes/gamerooms.py
tuicubserver/routes/games.py
tuicubserver/routes/users.py
tuicubserver/services/__init__.py
tuicubserver/services/auth.py
tuicubserver/services/game_toolkit.py
tuicubserver/services/gamerooms.py
tuicubserver/services/games.py
tuicubserver/services/rng.py
tuicubserver/services/tilesets.py
tuicubserver/services/users.py
tuicubserver-0.1.0.dist-info/METADATA
tuicubserver-0.1.0.dist-info/WHEEL
tuicubserver-0.1.0.dist-info/entry_points.txt
tuicubserver-0.1.0.dist-info/licenses/LICENSE
tuicubserver-0.1.0.dist-info/RECORD
