Metadata-Version: 2.1
Name: tuicubserver
Version: 0.1.0
Summary: Back-end for tuicub - online multiplayer board game in your terminal.
Project-URL: Documentation, https://github.com/tom-bartk/tuicubserver
Project-URL: Issues, https://github.com/tom-bartk/tuicubserver/issues
Project-URL: Source, https://github.com/tom-bartk/tuicubserver
Author-email: tombartk <tom.bartk@proton.me>
License-Expression: AGPL-3.0-or-later
License-File: LICENSE
Classifier: Development Status :: 4 - Beta
Classifier: Environment :: Console
Classifier: Framework :: Flask
Classifier: Intended Audience :: End Users/Desktop
Classifier: License :: OSI Approved :: GNU Affero General Public License v3 or later (AGPLv3+)
Classifier: Programming Language :: Python
Classifier: Programming Language :: Python :: 3.10
Classifier: Programming Language :: Python :: 3.11
Classifier: Programming Language :: Python :: 3.12
Classifier: Topic :: Games/Entertainment :: Board Games
Classifier: Typing :: Typed
Requires-Python: >=3.10
Requires-Dist: attrs==22.2.0
Requires-Dist: flask==3.0.0
Requires-Dist: marshmallow-generic==1.0.1
Requires-Dist: marshmallow==3.19.0
Requires-Dist: more-itertools==10.1.0
Requires-Dist: psycopg2==2.9.9
Requires-Dist: requests==2.31.0
Requires-Dist: sqlalchemy==2.0.22
Requires-Dist: structlog==23.2.0
Requires-Dist: theine==0.4.0
